setup.py
./etc/api-paste.ini
./etc/forward_client.cfg
./etc/forward_server.cfg
./etc/port_mapper.cfg
./etc/user_file
tcp_forward/__init__.py
tcp_forward/tcp_forward.py
tcp_forward.egg-info/PKG-INFO
tcp_forward.egg-info/SOURCES.txt
tcp_forward.egg-info/dependency_links.txt
tcp_forward.egg-info/requires.txt
tcp_forward.egg-info/top_level.txt
tcp_forward/common/__init__.py
tcp_forward/common/acceptor.py
tcp_forward/common/connector.py
tcp_forward/common/data_handler.py
tcp_forward/common/epoll_recever.py
tcp_forward/common/forward_data.py
tcp_forward/common/forward_event.py
tcp_forward/common/protocol_handler.py
tcp_forward/common/ring_buffer.py
tcp_forward/common/tools.py
tcp_forward/forward_client/__init__.py
tcp_forward/forward_client/conf.py
tcp_forward/forward_client/data_handler.py
tcp_forward/forward_client/forward_client.py
tcp_forward/forward_client/inner_worker.py
tcp_forward/forward_client/outer_worker.py
tcp_forward/forward_client/worker_manager.py
tcp_forward/forward_server/__init__.py
tcp_forward/forward_server/conf.py
tcp_forward/forward_server/data_handler.py
tcp_forward/forward_server/flow_static.py
tcp_forward/forward_server/forward_server.py
tcp_forward/forward_server/inner_worker.py
tcp_forward/forward_server/main.py
tcp_forward/forward_server/outer_worker.py
tcp_forward/forward_server/port_mapper.py
tcp_forward/forward_server/worker.py
tcp_forward/forward_server/worker_manager.py
tcp_forward/forward_server/rest_api/__init__.py
tcp_forward/forward_server/rest_api/api.py
tcp_forward/forward_server/rest_api/channel_api.py
tcp_forward/forward_server/rest_api/client_connection_api.py
tcp_forward/forward_server/rest_api/info_collection.py
tcp_forward/forward_server/rest_api/port_mapper_api.py
tcp_forward/forward_server/rest_api/test.py
tcp_forward/forward_server/rest_api/token.py
tcp_forward/forward_server/rest_api/token_verify.py
tcp_forward/forward_server/rest_api/user_pass.py
tools/tcp-forward