Metadata-Version: 1.0
Name: tcp-forward
Version: 1.0.4
Summary: forward data from an established tcp connection
Home-page: https://github.com/cao19881125/tcp_forward.git
Author: yuntao.cao
Author-email: yuntao.cao@nocsys.com.cn
License: MIT
Keywords: tcp-forward
Platform: any
